{  
   "time":{  
      "updated":"May 16, 2016 13:51:00 UTC",
      "updatedISO":"2016-05-16T13:51:00+00:00",
      "updateduk":"May 16, 2016 at 14:51 BST"
   },
   "disclaimer":"This data was produced from the CoinDesk Bitcoin Price Index (USD). Non-USD currency data converted using hourly conversion rate from openexchangerates.org",
   "bpi":{  
      "USD":{  
         "code":"USD",
         "rate":"456.6970",
         "description":"United States Dollar",
         "rate_float":456.697
      },
      "CAD":{  
         "code":"CAD",
         "rate":"590.4581",
         "description":"Canadian Dollar",
         "rate_float":590.4581
      }
   }
}